tomocompress/compressor.py
tomocompress/constants.py
tomocompress/hdf5_data.py
tomocompress/input_image_array.py
tomocompress/input_np_array.py
tomocompress/tomocompress_main.py
tomocompress/utils.py
tomocompress-0.2.4.dist-info/LICENSE.rst
tomocompress-0.2.4.dist-info/METADATA
tomocompress-0.2.4.dist-info/WHEEL
tomocompress-0.2.4.dist-info/entry_points.txt
tomocompress-0.2.4.dist-info/RECORD
