Metadata-Version: 2.1
Name: tomocompress
Version: 0.2.4
Summary: A command-line tool wrapping the blosc2-grok JPEG2K compressor for HDF5 tomographic data.
License: BSD-3-Clause
Author: SDM team, Alba,
Author-email: nsoler@cells.es
Requires-Python: >=3.12,<4.0
Classifier: License :: OSI Approved :: BSD License
Classifier: Programming Language :: Python :: 3
Classifier: Programming Language :: Python :: 3.12
Requires-Dist: argparse (>=1.4.0,<2.0.0)
Requires-Dist: blosc2 (>=2.7.1,<3.0.0)
Requires-Dist: blosc2-grok (>=0.3.3,<0.4.0)
Requires-Dist: h5py (>=3.12.1,<4.0.0)
Requires-Dist: hdf5plugin (>=4.4.0,<5.0.0)
Requires-Dist: jupyter (>=1.0.0,<2.0.0)
Requires-Dist: numpy (>=2.0,<3.0)
Requires-Dist: pillow (>=10.4.0,<11.0.0)
Requires-Dist: timeit-decorator (>=2.0.0,<3.0.0)
Requires-Dist: tqdm (>=4.67.1,<5.0.0)
